LICENSE
MANIFEST.in
README.md
setup.py
dongjak_dash_components/DongjakDashComponents.py
dongjak_dash_components/__init__.py
dongjak_dash_components/_imports_.py
dongjak_dash_components/dongjak_dash_components.js
dongjak_dash_components/metadata.json
dongjak_dash_components/package-info.json
dongjak_dash_components.egg-info/PKG-INFO
dongjak_dash_components.egg-info/SOURCES.txt
dongjak_dash_components.egg-info/dependency_links.txt
dongjak_dash_components.egg-info/top_level.txt